maccorcyclingdata/__init__.py
maccorcyclingdata/schedules.py
maccorcyclingdata/testdata.py
maccorcyclingdata/validate.py
tests/__init__.py
tests/test_schedules.py
tests/test_testdata.py
tests/test_validate.py
maccorcyclingdata-0.0.1.dist-info/LICENSE.txt
maccorcyclingdata-0.0.1.dist-info/METADATA
maccorcyclingdata-0.0.1.dist-info/WHEEL
maccorcyclingdata-0.0.1.dist-info/top_level.txt
maccorcyclingdata-0.0.1.dist-info/RECORD
