Metadata-Version: 2.1
Name: maccorcyclingdata
Version: 0.0.1
Summary: Python Package for Publicationto perform basic functions on Maccor Battery Cycling Data
Home-page: https://github.com/shriyachallam/maccorcyclingdata
Author: Shriya Challam
Author-email: shriyachallam10@gmail.com
License: MIT
Download-URL: https://pypi.org/project/maccorcyclingdata/
Keywords: Battery,Battery cycling,Maccor,Python
Platform: UNKNOWN
Requires-Dist: pandas (>=1.0.1)
Requires-Dist: numpy (>=1.18.1)
Requires-Dist: jupyterlab (>=1.2.6)
Requires-Dist: notebook (>=6.0.3)
Requires-Dist: pytest (>=6.0.2)
